Workbook
Name ano_dica: 'Viver de Renda'!$E$21
Name aporte: Simulador!$E$9
Name aporte_dica: 'Viver de Renda'!$E$20
Name dividendo_dica: 'Viver de Renda'!$E$24
Name gastos_fixos: 'Viver de Renda'!$E$7
Name lazer: 'Viver de Renda'!$E$8
Name montante: 'Viver de Renda'!$E$4
Name patrimonio: Simulador!$E$12
Name patrimonio_dica: 'Viver de Renda'!$E$23
Name qtd_ano: Simulador!$E$10
Name rendimento_carteira: Simulador!$E$5
Name rendimento_carteira2: 'Viver de Renda'!$E$9
Name reserva_emergencia: 'Viver de Renda'!$E$6
Name salario: Simulador!$E$4
Name salario_mensal: 'Viver de Renda'!$E$12
Name sugestao_investimento: Simulador!$E$6
Name taxa_dica: 'Viver de Renda'!$E$22
Name taxa_mensal: Simulador!$E$11
Name valor_investimento: 'Viver de Renda'!$E$5

Sheet Simulador
C3: CONFIGURAÇÕES
C4: Salário | E4: 4500
C5: Rendimento Carteira | E5: 0.01
C6: Sugestão de Investimento - 30% | E6: =E4*0.3 -> 1350
C8: INVESTIMENTO MENSAL
C9: Quanto investir por mês? | E9: 600
C10: Por quantos anos? | E10: 5
C11: Taxa de rendimento mensal? | E11: 0.01079
C12: Patrimônio acumulado? | E12: =FV(taxa_mensal,qtd_ano*12,aporte)*-1 -> 50266.148
C13: Dividendos Mensais? | E13: =patrimonio*rendimento_carteira -> 502.66148
C15: CENÁRIOS | E15: Dividendos
A16: 2 | C16: Quanto em 2 anos? | D16: =FV(taxa_mensal,$A16*12,aporte)*-1 -> 16336.576 | E16: =D16*rendimento_carteira -> 163.36576
A17: 5 | C17: Quanto em 5 anos? | D17: =FV(taxa_mensal,$A17*12,aporte)*-1 -> 50266.148 | E17: =D17*rendimento_carteira -> 502.66148
A18: 10 | C18: Quanto em 10 anos? | D18: =FV(taxa_mensal,$A18*12,aporte)*-1 -> 145970.53 | E18: =D18*rendimento_carteira -> 1459.7053
A19: 20 | C19: Quanto em 20 anos? | D19: =FV(taxa_mensal,$A19*12,aporte)*-1 -> 675119.04 | E19: =D19*rendimento_carteira -> 6751.1904
A20: 30 | C20: Quanto em 30 anos? | D20: =FV(taxa_mensal,$A20*12,aporte)*-1 -> 2593301.8 | E20: =D20*rendimento_carteira -> 25933.018
C22: PERFIL | D22: Conservador
C23: Valor a ser investido por mês | D23: =aporte -> 600
C25: TIPO FII | D25: Percentual Sugerido | E25: Valores
C26: PAPEL | D26: =VLOOKUP($D$22&"-"&$C26,Apoio!$A:$D,4,0) -> 0.3 | E26: =$D$23*$D26 -> 180
C27: TIJOLO | D27: =VLOOKUP($D$22&"-"&$C27,Apoio!$A:$D,4,0) -> 0.5 | E27: =$D$23*$D27 -> 300
C28: HÍBRIDOS | D28: =VLOOKUP($D$22&"-"&$C28,Apoio!$A:$D,4,0) -> 0.1 | E28: =$D$23*$D28 -> 60
C29: FOFs | D29: =VLOOKUP($D$22&"-"&$C29,Apoio!$A:$D,4,0) -> 0.1 | E29: =$D$23*$D29 -> 60
C30: DESENVOLVIMENTO | D30: =VLOOKUP($D$22&"-"&$C30,Apoio!$A:$D,4,0) -> 0 | E30: =$D$23*$D30 -> 0
C31: HOTELARIA | D31: =VLOOKUP($D$22&"-"&$C31,Apoio!$A:$D,4,0) -> 0 | E31: =$D$23*$D31 -> 0
E32: =SUM(E26:E31) -> 600

Sheet Viver de Renda
C3: CONFIGURAÇÕES - O QUE FAZER?
C4: Montante de acordo com seu salário para viver de renda, multiplique seu salário por: | E4: 200
C5: Valor Ideal invertir mensal para chegar ao montante, multiplique seu salário por: | E5: 0.3
C6: Valor necessário para reserva de emergência, multiplique seu salário por: | E6: 6
C7: Valor para gastos fixo, multiplique seu salário por: | E7: 0.6
C8: Valor máximo para gastar com lazer, multiplique seu salário por: | E8: 0.1
C9: Rendimento da Carteira | E9: 0.01
C11: RESULTADOS
C12: Salário? | E12: 1850
C13: Montante para Viver de Renda | E13: =salario_mensal*montante -> 370000
C14: Sugestão de Investimento | E14: =salario_mensal*valor_investimento -> 555
C15: Reserva de Emergância | E15: =salario_mensal*reserva_emergencia -> 11100
C16: Gastos Fixos | E16: =salario_mensal*gastos_fixos -> 1110
C17: Valor Máximo com Lazer | E17: =salario_mensal*lazer -> 185
C19: INVESTIMENTO MENSAL
C20: Quanto investir por mês? | E20: =$E$14 -> 555
C21: Por quantos anos? | E21: 10
C22: Taxa de rendimento mensal? | E22: 0.01079
C23: Patrimônio acumulado? | E23: =FV(taxa_dica,ano_dica*12,aporte_dica)*-1 -> 135022.74
C24: Dividendos Mensais? | E24: =patrimonio*rendimento_carteira2 -> 502.66148
C26: CENÁRIOS | E26: Dividendos
A27: 2 | C27: Quanto em 2 anos? | D27: =FV(taxa_dica,$A27*12,aporte_dica)*-1 -> 15111.333 | E27: =D27*rendimento_carteira2 -> 151.11333
A28: 5 | C28: Quanto em 5 anos? | D28: =FV(taxa_dica,$A28*12,aporte_dica)*-1 -> 46496.187 | E28: =D28*rendimento_carteira2 -> 464.96187
A29: 10 | C29: Quanto em 10 anos? | D29: =FV(taxa_dica,$A29*12,aporte_dica)*-1 -> 135022.74 | E29: =D29*rendimento_carteira2 -> 1350.2274
A30: 20 | C30: Quanto em 20 anos? | D30: =FV(taxa_dica,$A30*12,aporte_dica)*-1 -> 624485.11 | E30: =D30*rendimento_carteira2 -> 6244.8511
A31: 30 | C31: Quanto em 30 anos? | D31: =FV(taxa_dica,$A31*12,aporte_dica)*-1 -> 2398804.2 | E31: =D31*rendimento_carteira2 -> 23988.042

Sheet Apoio
A2: CHAVE | B2: PERFIL | C2: TIPO FII | D2: PERCENTUAL
A3: =B3&"-"&C3 -> CONSERVADOR-PAPEL | B3: CONSERVADOR | C3: PAPEL | D3: 0.3
A4: =B4&"-"&C4 -> CONSERVADOR-TIJOLO | B4: CONSERVADOR | C4: TIJOLO | D4: 0.5
A5: =B5&"-"&C5 -> CONSERVADOR-HÍBRIDOS | B5: CONSERVADOR | C5: HÍBRIDOS | D5: 0.1
A6: =B6&"-"&C6 -> CONSERVADOR-FOFs | B6: CONSERVADOR | C6: FOFs | D6: 0.1
A7: =B7&"-"&C7 -> CONSERVADOR-DESENVOLVIMENTO | B7: CONSERVADOR | C7: DESENVOLVIMENTO | D7: 0
A8: =B8&"-"&C8 -> CONSERVADOR-HOTELARIA | B8: CONSERVADOR | C8: HOTELARIA | D8: 0
A9: =B9&"-"&C9 -> MODERADO-PAPEL | B9: MODERADO | C9: PAPEL | D9: 0.32
A10: =B10&"-"&C10 -> MODERADO-TIJOLO | B10: MODERADO | C10: TIJOLO | D10: 0.35
A11: =B11&"-"&C11 -> MODERADO-HÍBRIDOS | B11: MODERADO | C11: HÍBRIDOS | D11: 0.08
A12: =B12&"-"&C12 -> MODERADO-FOFs | B12: MODERADO | C12: FOFs | D12: 0.05
A13: =B13&"-"&C13 -> MODERADO-DESENVOLVIMENTO | B13: MODERADO | C13: DESENVOLVIMENTO | D13: 0.1
A14: =B14&"-"&C14 -> MODERADO-HOTELARIA | B14: MODERADO | C14: HOTELARIA | D14: 0.1
... A20: =B20&"-"&C20 -> AGRESSIVO-HOTELARIA | B20: AGRESSIVO | C20: HOTELARIA | D20: 0.1
